web3research/__init__.py
web3research/web3research.py
web3research/btc/__init__.py
web3research/btc/formats.py
web3research/btc/provider.py
web3research/common/__init__.py
web3research/common/endpoints.py
web3research/common/type_convert.py
web3research/common/types.py
web3research/db/__init__.py
web3research/db/provider.py
web3research/eth/__init__.py
web3research/eth/formats.py
web3research/eth/provider.py
web3research/evm/__init__.py
web3research/evm/abi.py
web3research/evm/decoder.py
web3research/tron/__init__.py
web3research/tron/formats.py
web3research/tron/provider.py
web3research-0.0.10.dist-info/METADATA
web3research-0.0.10.dist-info/WHEEL
web3research-0.0.10.dist-info/licenses/LICENSE
web3research-0.0.10.dist-info/RECORD
