Metadata-Version: 2.4
Name: web3research
Version: 0.0.10
Summary: Python SDK for Web3Research Platform
Project-URL: Homepage, https://github.com/njublockchain/web3research-py
Project-URL: Repository, https://github.com/njublockchain/web3research-py
Project-URL: Documentation, https://github.com/njublockchain/web3research-py
Project-URL: Bug Tracker, https://github.com/njublockchain/web3research-py/issues
Author-email: Command <me@c0mm4nd.com>
License-Expression: MIT
License-File: LICENSE
Keywords: blockchain,ethereum,tron,web3,web3.py,web3research
Classifier: License :: OSI Approved :: MIT License
Classifier: Operating System :: OS Independent
Classifier: Programming Language :: Python :: 3
Requires-Python: ~=3.8
Requires-Dist: base58<3,>=2.1.1
Requires-Dist: clickhouse-connect<0.9,>=0.8.17
Requires-Dist: web3~=7.12
